MANIFEST.in
README.md
setup.py
testfile.py
alaya/__init__.py
alaya/exceptions.py
alaya/fvnhash.py
alaya/param_encode.py
alaya/packages/__init__.py
alaya/packages/eth_abi/__init__.py
alaya/packages/eth_abi/abi.py
alaya/packages/eth_abi/base.py
alaya/packages/eth_abi/constants.py
alaya/packages/eth_abi/decoding.py
alaya/packages/eth_abi/encoding.py
alaya/packages/eth_abi/exceptions.py
alaya/packages/eth_abi/grammar.py
alaya/packages/eth_abi/registry.py
alaya/packages/eth_abi/utils/__init__.py
alaya/packages/eth_abi/utils/numeric.py
alaya/packages/eth_abi/utils/padding.py
alaya/packages/eth_abi/utils/parsing.py
alaya/packages/eth_typing/__init__.py
alaya/packages/eth_typing/abi.py
alaya/packages/eth_typing/bls.py
alaya/packages/eth_typing/encoding.py
alaya/packages/eth_typing/enums.py
alaya/packages/eth_typing/ethpm.py
alaya/packages/eth_typing/evm.py
alaya/packages/eth_utils/__init__.py
alaya/packages/eth_utils/__main__.py
alaya/packages/eth_utils/abi.py
alaya/packages/eth_utils/address.py
alaya/packages/eth_utils/applicators.py
alaya/packages/eth_utils/conversions.py
alaya/packages/eth_utils/crypto.py
alaya/packages/eth_utils/currency.py
alaya/packages/eth_utils/debug.py
alaya/packages/eth_utils/decorators.py
alaya/packages/eth_utils/encoding.py
alaya/packages/eth_utils/exceptions.py
alaya/packages/eth_utils/functional.py
alaya/packages/eth_utils/hexadecimal.py
alaya/packages/eth_utils/humanize.py
alaya/packages/eth_utils/logging.py
alaya/packages/eth_utils/module_loading.py
alaya/packages/eth_utils/numeric.py
alaya/packages/eth_utils/toolz.py
alaya/packages/eth_utils/types.py
alaya/packages/eth_utils/units.py
alaya/packages/eth_utils/curried/__init__.py
alaya/packages/eth_utils/typing/__init__.py
alaya/packages/eth_utils/typing/misc.py
alaya/packages/platon_keys/__init__.py
alaya/packages/platon_keys/constants.py
alaya/packages/platon_keys/datatypes.py
alaya/packages/platon_keys/exceptions.py
alaya/packages/platon_keys/main.py
python_migrate_tool.egg-info/PKG-INFO
python_migrate_tool.egg-info/SOURCES.txt
python_migrate_tool.egg-info/dependency_links.txt
python_migrate_tool.egg-info/not-zip-safe
python_migrate_tool.egg-info/requires.txt
python_migrate_tool.egg-info/top_level.txt
